selectlib.pypy39-pp73-darwin.so
selectlib-1.0.4.dist-info/RECORD
selectlib-1.0.4.dist-info/LICENSE
selectlib-1.0.4.dist-info/WHEEL
selectlib-1.0.4.dist-info/top_level.txt
selectlib-1.0.4.dist-info/METADATA
