Metadata-Version: 2.1
Name: selectlib
Version: 1.0.4
Summary: Lightweight C extension module for Python that implements several in‑place selection algorithms.
Home-page: https://github.com/grantjenks/python-selectlib
Author: Grant Jenks
Author-email: grant.jenks@gmail.com
License: Apache 2.0
Classifier: Development Status :: 5 - Production/Stable
Classifier: Intended Audience :: Developers
Classifier: Topic :: Software Development :: Libraries
Classifier: License :: OSI Approved :: Apache Software License
Classifier: Programming Language :: C
Classifier: Programming Language :: Python
Classifier: Programming Language :: Python :: 3
Classifier: Programming Language :: Python :: Implementation :: CPython
Requires-Python: >=3.8
License-File: LICENSE
